htbrecon/__init__.py
htbrecon/banner.py
htbrecon/main.py
htbrecon/state.py
htbrecon/tools/__init__.py
htbrecon/tools/ai.py
htbrecon/tools/gobuster.py
htbrecon/tools/hosts.py
htbrecon/tools/nmap.py
htbrecon/tools/subdomains.py
htbrecon-0.1.12.dist-info/METADATA
htbrecon-0.1.12.dist-info/WHEEL
htbrecon-0.1.12.dist-info/entry_points.txt
htbrecon-0.1.12.dist-info/top_level.txt
htbrecon-0.1.12.dist-info/RECORD
